Metadata-Version: 2.1
Name: pytrapment
Version: 1.0.1
Summary: pytrapment: create an entrapment database for proteomic mass spectrometry analysis
Home-page: UNKNOWN
Author: Sven Giese
Author-email: sven.giese@hpi.de
License: Apache License 2.0
Project-URL: Bug Tracker, https://github.com/gieses/pytrapment/issues
Project-URL: Source Code, https://github.com/gieses/pytrapment
Project-URL: Documentation, https://github.com/gieses/pytrapment
Project-URL: Homepage, https://github.com/gieses/pytrapment
Keywords: Proteomics,machine learning,uniprot,fasta
Platform: UNKNOWN
Classifier: Programming Language :: Python
Classifier: Programming Language :: Python :: 3.8
Classifier: Programming Language :: Python :: Implementation :: PyPy
Requires-Python: >=3.8.0
